MANIFEST.in
README.rst
pyproject.toml
requirements.txt
setup.cfg
setup.py
t_qa/__init__.py
t_qa/columns_blocks.py
t_qa/config.py
t_qa/exception.py
t_qa/logger.py
t_qa/models.py
t_qa/qa.py
t_qa/run_assets.py
t_qa/status.py
t_qa/utils.py
t_qa/workitems.py
t_qa.egg-info/PKG-INFO
t_qa.egg-info/SOURCES.txt
t_qa.egg-info/dependency_links.txt
t_qa.egg-info/not-zip-safe
t_qa.egg-info/requires.txt
t_qa.egg-info/top_level.txt
t_qa/excel_processing/__init__.py
t_qa/excel_processing/excel_report.py
t_qa/excel_processing/google_sheet.py
t_qa/excel_processing/report.py
t_qa/goole_api/__init__.py
t_qa/goole_api/account.py
t_qa/goole_api/google_drive_service.py
t_qa/goole_api/goolge_services.py
test/test_qa.py