Metadata-Version: 2.1
Name: t_qa
Version: 0.1.19
Summary:  T - QA library designed to automate the testing process
Home-page: https://www.thoughtful.ai/
Author: Thoughtful
Author-email: support@thoughtful.ai
Keywords: t_qa
Classifier: Intended Audience :: Developers
Classifier: Natural Language :: English
Classifier: Programming Language :: Python :: 3
Classifier: Programming Language :: Python :: 3.9
Requires-Python: >=3.9
Requires-Dist: google-api-python-client>=2.135.0
Requires-Dist: google-auth-httplib2>=0.2.0
Requires-Dist: google-auth-oauthlib>=1.2.0
Requires-Dist: gspread>=6.1.2
Requires-Dist: retry>=0.9.2
Requires-Dist: coverage>=7.4.2
Requires-Dist: t_bug_catcher>=0.5.8
